LogCollectionFormatter2/__init__.py
LogCollectionFormatter2/base_log.py
LogCollectionFormatter2/insert_mq_tools.py
LogCollectionFormatter2/main_log.py
LogCollectionFormatter2-2.0.3.dist-info/LICENSE
LogCollectionFormatter2-2.0.3.dist-info/METADATA
LogCollectionFormatter2-2.0.3.dist-info/WHEEL
LogCollectionFormatter2-2.0.3.dist-info/top_level.txt
LogCollectionFormatter2-2.0.3.dist-info/RECORD
