Metadata-Version: 2.1
Name: LogCollectionFormatter2
Version: 2.0.3
Summary: LogCollectionFormatter2 是一个专为Python应用程序设计的日志记录和消息队列工具库， 提供强大功能，帮助开发者轻松追踪应用状态和发送日志消息到消息队列。
Author: Unnamed great master
Author-email: <gqylpy@outlook.com>
License: BSD 3-Clause
Project-URL: Source, https://github.com/2018-11-27/LogCollectionFormatter2
Classifier: Development Status :: 3 - Alpha
Classifier: Intended Audience :: Developers
Classifier: License :: OSI Approved :: BSD License
Classifier: Natural Language :: Chinese (Simplified)
Classifier: Natural Language :: English
Classifier: Operating System :: OS Independent
Classifier: Topic :: Software Development :: Libraries :: Python Modules
Classifier: Topic :: Internet :: Log Analysis
Classifier: Programming Language :: Python :: 2.7
Classifier: Programming Language :: Python :: 3.5
Classifier: Programming Language :: Python :: 3.6
Classifier: Programming Language :: Python :: 3.7
Classifier: Programming Language :: Python :: 3.8
Classifier: Programming Language :: Python :: 3.9
Classifier: Programming Language :: Python :: 3.10
Classifier: Programming Language :: Python :: 3.11
Classifier: Programming Language :: Python :: 3.12
Requires-Python: >=2.7, !=3.0.*, !=3.1.*, !=3.2.*, !=3.3.*, !=3.4.*
License-File: LICENSE
Requires-Dist: gevent
Requires-Dist: kombu
Requires-Dist: Flask
